{
  "people": [
    {
      "id": 1,
      "name": "Федор",
      "surname": "Рыбалко (Родоначальник)",
      "middlename": null,
      "gender": "M",
      "birthDate": "1870-03-05",
      "deathDate": "1946-07-20",
      "birthPlace": "Харьковская область",
      "fatherId": null,
      "motherId": null,
      "spouseId": 2,
      "biography": null,
      "photo": null,
      "photos": []
    },
    {
      "id": 2,
      "name": "Мария",
      "surname": "Рыбалко",
      "middlename": null,
      "gender": "F",
      "birthDate": "1873-01-20",
      "deathDate": "1947-05-09",
      "birthPlace": null,
      "fatherId": null,
      "motherId": null,
      "spouseId": 1,
      "biography": null,
      "photo": null,
      "photos": []
    },
    {
      "id": 3,
      "name": "Оксана",
      "surname": "Сагурова (Рыбалко)",
      "middlename": "Федоровна",
      "gender": "F",
      "birthDate": "1918-09-11",
      "deathDate": "1989-02-25",
      "birthPlace": "Харьковская область",
      "fatherId": 1,
      "motherId": 2,
      "spouseId": 4,
      "biography": null,
      "photo": "photos/avatars/Баба_Оксана_3.jpg",
      "photos": [
        "",
        ""
      ]
    },
    {
      "id": 4,
      "name": "Андрей",
      "surname": "Сагуров",
      "middlename": "Лавреньтевич",
      "gender": "M",
      "birthDate": "1915-08-29",
      "deathDate": "1943-09-23",
      "birthPlace": "Харьковская область",
      "fatherId": 5,
      "motherId": 6,
      "spouseId": 3,
      "biography": null,
      "photo": "photos/avatars/Андрей_дед.jpg",
      "photos": []
    },
    {
      "id": 5,
      "name": "Лаврентий",
      "surname": "Сагуров (Родоначальник)",
      "middlename": null,
      "gender": "M",
      "birthDate": "1915-01-01",
      "deathDate": "1936-01-01",
      "birthPlace": "Харьковская область",
      "fatherId": null,
      "motherId": null,
      "spouseId": 6,
      "biography": null,
      "photo": null,
      "photos": []
    },
    {
      "id": 6,
      "name": "Соломея",
      "surname": "Сагурова",
      "middlename": null,
      "gender": "F",
      "birthDate": "1870-01-01",
      "deathDate": "1938-01-01",
      "birthPlace": "Харьковская область",
      "fatherId": null,
      "motherId": null,
      "spouseId": 5,
      "biography": null,
      "photo": null,
      "photos": []
    },
    {
      "id": 7,
      "name": "Петр",
      "surname": "Сагуров",
      "middlename": "Петрович",
      "gender": "M",
      "birthDate": "1940-09-01",
      "deathDate": "2004-12-03",
      "birthPlace": "Харьковская область",
      "fatherId": 4,
      "motherId": 3,
      "spouseId": 15,
      "biography": null,
      "photo": null,
      "photos": []
    },
    {
      "id": 8,
      "name": "Лидия",
      "surname": "Вустина (Сагурова)",
      "middlename": "Андреевна",
      "gender": "F",
      "birthDate": "1938-09-01",
      "deathDate": null,
      "birthPlace": "Харьковская область",
      "fatherId": 4,
      "motherId": 3,
      "spouseId": 9,
      "biography": null,
      "photo": "photos/avatars/теть_Лида.jpg",
      "photos": [
        "",
        "",
        ""
      ]
    },
    {
      "id": 9,
      "name": "Аркадий",
      "surname": "Вустин",
      "middlename": "Дмитриевич",
      "gender": "M",
      "birthDate": "1937-01-01",
      "deathDate": "2014-01-17",
      "birthPlace": "пос. Космос, Алмаатинская область",
      "fatherId": 10,
      "motherId": 11,
      "spouseId": 8,
      "biography": "НОВЫЙ НОВЫЙ",
      "photo": "photos/avatars/Дядь_Аркадий.jpg",
      "photos": [
        ""
      ]
    },
    {
      "id": 10,
      "name": "Дмитрий",
      "surname": "Вустин (Родоначальник)",
      "middlename": "Никифорович",
      "gender": "M",
      "birthDate": "1907-01-01",
      "deathDate": "1947-01-01",
      "birthPlace": "Белорусь   УТОЧНИТЬ МЕСто",
      "fatherId": null,
      "motherId": null,
      "spouseId": null,
      "biography": null,
      "photo": null,
      "photos": []
    },
    {
      "id": 11,
      "name": "Елена",
      "surname": "Вустина (Максимова)",
      "middlename": null,
      "gender": "F",
      "birthDate": "1910-05-17",
      "deathDate": "1994-06-01",
      "birthPlace": "Белорусь",
      "fatherId": null,
      "motherId": null,
      "spouseId": 10,
      "biography": null,
      "photo": null,
      "photos": []
    },
    {
      "id": 12,
      "name": "Ольга",
      "surname": "Витошкина (Вустина)",
      "middlename": "Аркадьевна",
      "gender": "F",
      "birthDate": null,
      "deathDate": null,
      "birthPlace": null,
      "fatherId": 9,
      "motherId": 8,
      "spouseId": 23,
      "biography": null,
      "photo": "photos/avatars/Оля.jpg",
      "photos": [
        ""
      ]
    },
    {
      "id": 13,
      "name": "Неля",
      "surname": "Мезько (Вустина)",
      "middlename": null,
      "gender": "F",
      "birthDate": "1962-09-04",
      "deathDate": null,
      "birthPlace": "пос. Космос, Алмаатинская область",
      "fatherId": 9,
      "motherId": 8,
      "spouseId": 22,
      "biography": null,
      "photo": "photos/avatars/Неля.jpg",
      "photos": [
        ""
      ]
    },
    {
      "id": 14,
      "name": "Александр",
      "surname": "Вустин",
      "middlename": "Аркадьевич",
      "gender": "M",
      "birthDate": "1968-12-22",
      "deathDate": null,
      "birthPlace": "пос. Космос, Алмаатинская область",
      "fatherId": 9,
      "motherId": 8,
      "spouseId": 33,
      "biography": null,
      "photo": "photos/avatars/Александр.jpg",
      "photos": [
        "",
        ""
      ]
    },
    {
      "id": 15,
      "name": "Галина",
      "surname": "Сагурова (Гвоздева)",
      "middlename": "Анатольевна",
      "gender": "F",
      "birthDate": "1939-12-07",
      "deathDate": "2016-10-23",
      "birthPlace": null,
      "fatherId": null,
      "motherId": null,
      "spouseId": 7,
      "biography": null,
      "photo": "photos/avatars/мама-1.jpg",
      "photos": [
        "",
        "",
        "",
        ""
      ]
    },
    {
      "id": 16,
      "name": "Андрей",
      "surname": "Сагуров",
      "middlename": "Петрович",
      "gender": "M",
      "birthDate": "1966-05-25",
      "deathDate": null,
      "birthPlace": "г.Балхаш, Казахская ССР",
      "fatherId": 7,
      "motherId": 15,
      "spouseId": 19,
      "biography": null,
      "photo": null,
      "photos": []
    },
    {
      "id": 17,
      "name": "Дмитрий",
      "surname": "Сагуров",
      "middlename": "Петрович",
      "gender": "M",
      "birthDate": "1969-09-20",
      "deathDate": null,
      "birthPlace": "Вышевогорск, Челябинска область",
      "fatherId": 7,
      "motherId": 15,
      "spouseId": 21,
      "biography": null,
      "photo": "photos/avatars/Дмитрий.jpg",
      "photos": [
        "",
        ""
      ]
    },
    {
      "id": 18,
      "name": "Екатерина",
      "surname": "Виноградова (Сагурова)",
      "middlename": "Андреевна",
      "gender": "F",
      "birthDate": "1993-07-12",
      "deathDate": null,
      "birthPlace": "город Санкт-Петербург",
      "fatherId": 16,
      "motherId": 19,
      "spouseId": 50,
      "biography": null,
      "photo": "photos/avatars/КатяСаг.jpg",
      "photos": [
        "",
        ""
      ]
    },
    {
      "id": 19,
      "name": "Татьяна",
      "surname": "Сагурова (Быстрова)",
      "middlename": "Анатольевна",
      "gender": "F",
      "birthDate": "1968-04-01",
      "deathDate": null,
      "birthPlace": null,
      "fatherId": null,
      "motherId": null,
      "spouseId": 16,
      "biography": null,
      "photo": null,
      "photos": []
    },
    {
      "id": 20,
      "name": "Ирина",
      "surname": "Сагурова",
      "middlename": "Андреевна",
      "gender": "F",
      "birthDate": "1995-06-08",
      "deathDate": null,
      "birthPlace": "г.Санкт-Петербург",
      "fatherId": 16,
      "motherId": 19,
      "spouseId": null,
      "biography": null,
      "photo": "photos/avatars/Ира-1.jpg",
      "photos": [
        "",
        "",
        ""
      ]
    },
    {
      "id": 21,
      "name": "Мария",
      "surname": "Сагурова",
      "middlename": "Рахимовна",
      "gender": "F",
      "birthDate": "1978-10-15",
      "deathDate": null,
      "birthPlace": null,
      "fatherId": null,
      "motherId": null,
      "spouseId": 17,
      "biography": null,
      "photo": "photos/avatars/Мария.jpg",
      "photos": []
    },
    {
      "id": 22,
      "name": "Петр",
      "surname": "Мезько",
      "middlename": "Ерофеевич",
      "gender": "M",
      "birthDate": "1959-10-29",
      "deathDate": null,
      "birthPlace": "совхоз Джанашар, Алмаатинская область, Каз ССЗ",
      "fatherId": null,
      "motherId": null,
      "spouseId": 13,
      "biography": null,
      "photo": "photos/avatars/Петр.jpg",
      "photos": [
        ""
      ]
    },
    {
      "id": 23,
      "name": "Александр",
      "surname": "Ветошкин",
      "middlename": "Васильевич",
      "gender": "M",
      "birthDate": "1954-06-07",
      "deathDate": "2007-06-11",
      "birthPlace": "совхоз Космос, Алмаатинска обл., Каз. ССР",
      "fatherId": null,
      "motherId": null,
      "spouseId": 12,
      "biography": null,
      "photo": null,
      "photos": []
    },
    {
      "id": 24,
      "name": "Павел",
      "surname": "Ветошкин",
      "middlename": "Александрович",
      "gender": "M",
      "birthDate": "1979-05-21",
      "deathDate": "2024-02-06",
      "birthPlace": "г.Алма-Ата",
      "fatherId": 23,
      "motherId": 12,
      "spouseId": null,
      "biography": null,
      "photo": null,
      "photos": []
    },
    {
      "id": 25,
      "name": "Константин",
      "surname": "Ветошкин",
      "middlename": "Александрович",
      "gender": "M",
      "birthDate": "1983-02-08",
      "deathDate": null,
      "birthPlace": "г.Алма-Ата",
      "fatherId": 23,
      "motherId": 12,
      "spouseId": null,
      "biography": null,
      "photo": "photos/avatars/Константин.jpg",
      "photos": []
    },
    {
      "id": 26,
      "name": "Ева",
      "surname": "Ветошкина",
      "middlename": "Константиновна",
      "gender": "F",
      "birthDate": "1010-11-07",
      "deathDate": null,
      "birthPlace": null,
      "fatherId": 25,
      "motherId": null,
      "spouseId": null,
      "biography": null,
      "photo": "photos/avatars/Ева.jpg",
      "photos": []
    },
    {
      "id": 27,
      "name": "Зоя",
      "surname": "Ветошкина",
      "middlename": "Константиновна",
      "gender": "F",
      "birthDate": "2012-07-07",
      "deathDate": null,
      "birthPlace": null,
      "fatherId": 25,
      "motherId": null,
      "spouseId": null,
      "biography": null,
      "photo": "photos/avatars/Зоя.jpg",
      "photos": [
        ""
      ]
    },
    {
      "id": 28,
      "name": "Олеся",
      "surname": "Брантд(Мезько)",
      "middlename": "Петровна",
      "gender": "F",
      "birthDate": "1982-05-23",
      "deathDate": null,
      "birthPlace": "г.Алма-Ата",
      "fatherId": 22,
      "motherId": 13,
      "spouseId": 44,
      "biography": null,
      "photo": "photos/avatars/Олеся.jpg",
      "photos": [
        ""
      ]
    },
    {
      "id": 29,
      "name": "Максим",
      "surname": "Мезько",
      "middlename": "Петрович",
      "gender": "M",
      "birthDate": "1987-11-17",
      "deathDate": null,
      "birthPlace": "г.Алма-Ата",
      "fatherId": 22,
      "motherId": 13,
      "spouseId": null,
      "biography": null,
      "photo": "photos/avatars/Максим.jpg",
      "photos": []
    },
    {
      "id": 31,
      "name": "Валерия",
      "surname": "Брантд",
      "middlename": "Алексеевна",
      "gender": "F",
      "birthDate": "2010-08-26",
      "deathDate": null,
      "birthPlace": "г.Алма-Ата",
      "fatherId": null,
      "motherId": 28,
      "spouseId": null,
      "biography": null,
      "photo": "photos/avatars/Валерия.jpg",
      "photos": [
        ""
      ]
    },
    {
      "id": 32,
      "name": "Елена",
      "surname": "Вустина",
      "middlename": "Павловна",
      "gender": "F",
      "birthDate": "1970-09-18",
      "deathDate": null,
      "birthPlace": "гор.Алма-Ата",
      "fatherId": null,
      "motherId": null,
      "spouseId": 14,
      "biography": null,
      "photo": null,
      "photos": []
    },
    {
      "id": 33,
      "name": "Оксана",
      "surname": "Вустина",
      "middlename": "Владимировна",
      "gender": "F",
      "birthDate": "1975-03-31",
      "deathDate": null,
      "birthPlace": "гор.Алма-Ата",
      "fatherId": null,
      "motherId": null,
      "spouseId": 14,
      "biography": null,
      "photo": "photos/avatars/Оксана.jpg",
      "photos": []
    },
    {
      "id": 34,
      "name": "Юля",
      "surname": "Ищенко (Вустина)",
      "middlename": "Александровна",
      "gender": "F",
      "birthDate": "2013-01-03",
      "deathDate": null,
      "birthPlace": "гор.Алм-Ата",
      "fatherId": 14,
      "motherId": 32,
      "spouseId": 55,
      "biography": null,
      "photo": "photos/avatars/ЮляВустина.jpg",
      "photos": []
    },
    {
      "id": 35,
      "name": "Андрей",
      "surname": "Вустин",
      "middlename": "Александрович",
      "gender": "M",
      "birthDate": "1995-05-14",
      "deathDate": null,
      "birthPlace": "гор.Алма-Ата",
      "fatherId": 14,
      "motherId": 32,
      "spouseId": 51,
      "biography": null,
      "photo": "photos/avatars/АндрейВустин.jpg",
      "photos": []
    },
    {
      "id": 36,
      "name": "Сабрина",
      "surname": "Кадиева",
      "middlename": "Мухамед-Али",
      "gender": "F",
      "birthDate": "2013-01-03",
      "deathDate": null,
      "birthPlace": "гор.Алма-Ата",
      "fatherId": 54,
      "motherId": 34,
      "spouseId": null,
      "biography": null,
      "photo": "photos/avatars/Сабрина.jpeg",
      "photos": []
    },
    {
      "id": 37,
      "name": "Руслан",
      "surname": "Ищенко",
      "middlename": "Романович",
      "gender": "M",
      "birthDate": "2024-03-22",
      "deathDate": null,
      "birthPlace": "гор.Алма-Ата",
      "fatherId": 53,
      "motherId": 34,
      "spouseId": null,
      "biography": null,
      "photo": null,
      "photos": []
    },
    {
      "id": 38,
      "name": "Софья",
      "surname": "Вустина",
      "middlename": "Александровна",
      "gender": "F",
      "birthDate": "2010-04-23",
      "deathDate": null,
      "birthPlace": null,
      "fatherId": 14,
      "motherId": 33,
      "spouseId": null,
      "biography": null,
      "photo": "photos/avatars/Софья.jpg",
      "photos": []
    },
    {
      "id": 39,
      "name": "Аарон",
      "surname": "Вустин",
      "middlename": null,
      "gender": "M",
      "birthDate": "2022-05-31",
      "deathDate": null,
      "birthPlace": "гор.Алма-Ата",
      "fatherId": 35,
      "motherId": null,
      "spouseId": null,
      "biography": null,
      "photo": null,
      "photos": []
    },
    {
      "id": 40,
      "name": "Антон",
      "surname": "Сагуров",
      "middlename": "Дмитриевич",
      "gender": "M",
      "birthDate": "1995-10-29",
      "deathDate": null,
      "birthPlace": "гор.Текели, Казахстан",
      "fatherId": 17,
      "motherId": 42,
      "spouseId": 48,
      "biography": null,
      "photo": "photos/avatars/Антон.jpg",
      "photos": []
    },
    {
      "id": 41,
      "name": "Егор",
      "surname": "Сагуров",
      "middlename": "Дмитриевич",
      "gender": "M",
      "birthDate": "2000-12-11",
      "deathDate": null,
      "birthPlace": "гор.Текели, Казахстан",
      "fatherId": 17,
      "motherId": 21,
      "spouseId": null,
      "biography": null,
      "photo": "photos/avatars/Егор.jpg",
      "photos": []
    },
    {
      "id": 42,
      "name": "Лариса",
      "surname": "Сагурова (Кудык)",
      "middlename": "Александровна",
      "gender": "F",
      "birthDate": "1968-11-13",
      "deathDate": null,
      "birthPlace": null,
      "fatherId": null,
      "motherId": null,
      "spouseId": 17,
      "biography": null,
      "photo": null,
      "photos": []
    },
    {
      "id": 43,
      "name": "Олег",
      "surname": "Сагуров",
      "middlename": "Дмитреевич",
      "gender": "M",
      "birthDate": "2003-02-07",
      "deathDate": null,
      "birthPlace": "гор. Текели",
      "fatherId": 17,
      "motherId": 21,
      "spouseId": null,
      "biography": null,
      "photo": "photos/avatars/Олег.jpg",
      "photos": []
    },
    {
      "id": 44,
      "name": "Алексей",
      "surname": "Брандт",
      "middlename": null,
      "gender": "M",
      "birthDate": null,
      "deathDate": null,
      "birthPlace": null,
      "fatherId": null,
      "motherId": null,
      "spouseId": 28,
      "biography": null,
      "photo": "photos/avatars/Алексей_Олеся.jpg",
      "photos": []
    },
    {
      "id": 45,
      "name": "Артем",
      "surname": "Брандт",
      "middlename": "Алексеевич",
      "gender": "M",
      "birthDate": null,
      "deathDate": null,
      "birthPlace": null,
      "fatherId": 44,
      "motherId": 28,
      "spouseId": null,
      "biography": null,
      "photo": "photos/avatars/Артем.jpg",
      "photos": []
    },
    {
      "id": 46,
      "name": "Валерия",
      "surname": "Брандт",
      "middlename": "Алексеевна",
      "gender": "F",
      "birthDate": null,
      "deathDate": null,
      "birthPlace": null,
      "fatherId": 44,
      "motherId": 28,
      "spouseId": null,
      "biography": null,
      "photo": "photos/avatars/Валерия.jpg",
      "photos": []
    },
    {
      "id": 47,
      "name": "Роман",
      "surname": "!!!!!",
      "middlename": null,
      "gender": "M",
      "birthDate": null,
      "deathDate": null,
      "birthPlace": null,
      "fatherId": null,
      "motherId": null,
      "spouseId": 34,
      "biography": null,
      "photo": "photos/avatars/Роман_муж_Юли.jpg",
      "photos": []
    },
    {
      "id": 48,
      "name": "Анастасия",
      "surname": "Алексенцева",
      "middlename": "Станиславовна",
      "gender": "F",
      "birthDate": "1993-07-07",
      "deathDate": null,
      "birthPlace": "город Талды Корган",
      "fatherId": null,
      "motherId": null,
      "spouseId": 40,
      "biography": null,
      "photo": null,
      "photos": []
    },
    {
      "id": 49,
      "name": "Рада",
      "surname": "Сагурова",
      "middlename": "Антоновна",
      "gender": "F",
      "birthDate": null,
      "deathDate": null,
      "birthPlace": null,
      "fatherId": 40,
      "motherId": 48,
      "spouseId": null,
      "biography": null,
      "photo": "photos/avatars/Рада.jpg",
      "photos": []
    },
    {
      "id": 50,
      "name": "Сергей",
      "surname": "Виноградов",
      "middlename": null,
      "gender": "M",
      "birthDate": "1995-02-01",
      "deathDate": null,
      "birthPlace": "город Санк-Петербург",
      "fatherId": null,
      "motherId": null,
      "spouseId": 18,
      "biography": null,
      "photo": "photos/avatars/СергейВин.jpg",
      "photos": [
        ""
      ]
    },
    {
      "id": 51,
      "name": "Алина",
      "surname": "Вустина (Ефремова)",
      "middlename": "Витальевна",
      "gender": "F",
      "birthDate": "1998-02-01",
      "deathDate": null,
      "birthPlace": null,
      "fatherId": null,
      "motherId": null,
      "spouseId": 35,
      "biography": null,
      "photo": "photos/avatars/АлинаВустина.jpg",
      "photos": []
    },
    {
      "id": 52,
      "name": "Аарон",
      "surname": "Вустин",
      "middlename": "Андреевич",
      "gender": "M",
      "birthDate": "2022-05-31",
      "deathDate": null,
      "birthPlace": null,
      "fatherId": 35,
      "motherId": 51,
      "spouseId": null,
      "biography": null,
      "photo": "photos/avatars/АронВустин.jpg",
      "photos": []
    },
    {
      "id": 53,
      "name": "Роман",
      "surname": "Ищенко",
      "middlename": null,
      "gender": "M",
      "birthDate": "1989-11-08",
      "deathDate": null,
      "birthPlace": null,
      "fatherId": null,
      "motherId": null,
      "spouseId": 34,
      "biography": null,
      "photo": "photos/avatars/Роман_муж_Юли.jpg",
      "photos": []
    },
    {
      "id": 54,
      "name": "Мухамед-Али",
      "surname": "Кадиев",
      "middlename": null,
      "gender": "M",
      "birthDate": null,
      "deathDate": null,
      "birthPlace": null,
      "fatherId": null,
      "motherId": null,
      "spouseId": null,
      "biography": null,
      "photo": null,
      "photos": []
    },
    {
      "id": 56,
      "name": "Варавара",
      "surname": "Гвоздева",
      "middlename": "Васильевна",
      "gender": "F",
      "birthDate": null,
      "deathDate": null,
      "birthPlace": null,
      "fatherId": null,
      "motherId": null,
      "spouseId": 57,
      "biography": null,
      "photo": "photos/gallery/ Баба_ВаряГвоздева.jpg",
      "photos": [
        ""
      ]
    },
    {
      "id": 57,
      "name": "Анатолий",
      "surname": "Гвоздев",
      "middlename": "Трофимович",
      "gender": "M",
      "birthDate": null,
      "deathDate": null,
      "birthPlace": null,
      "fatherId": null,
      "motherId": null,
      "spouseId": 56,
      "biography": null,
      "photo": null,
      "photos": []
    },
    {
      "id": 58,
      "name": "Валентин",
      "surname": "Гвоздев",
      "middlename": "Анатольевич",
      "gender": "M",
      "birthDate": null,
      "deathDate": null,
      "birthPlace": null,
      "fatherId": 56,
      "motherId": 57,
      "spouseId": null,
      "biography": null,
      "photo": null,
      "photos": []
    },
    {
      "id": 59,
      "name": "Вера",
      "surname": "Рылова (Гвоздева)",
      "middlename": "Анатольевна",
      "gender": "F",
      "birthDate": null,
      "deathDate": null,
      "birthPlace": null,
      "fatherId": 56,
      "motherId": 57,
      "spouseId": null,
      "biography": null,
      "photo": "photos/avatars/Рылова_ГвоздеваВера.jpg",
      "photos": []
    },
    {
      "id": 60,
      "name": "Николай",
      "surname": "Гвоздев",
      "middlename": "Анатольевич",
      "gender": "M",
      "birthDate": null,
      "deathDate": null,
      "birthPlace": null,
      "fatherId": 56,
      "motherId": 57,
      "spouseId": null,
      "biography": null,
      "photo": null,
      "photos": []
    },
    {
      "id": 61,
      "name": "Елизавета",
      "surname": "Батунина",
      "middlename": "Максимовна",
      "gender": "F",
      "birthDate": null,
      "deathDate": null,
      "birthPlace": null,
      "fatherId": null,
      "motherId": null,
      "spouseId": null,
      "biography": null,
      "photo": null,
      "photos": []
    },
    {
      "id": 62,
      "name": "Олег",
      "surname": "Быстров",
      "middlename": "Анатольевич",
      "gender": "M",
      "birthDate": "1962-05-08",
      "deathDate": null,
      "birthPlace": null,
      "fatherId": null,
      "motherId": null,
      "spouseId": null,
      "biography": null,
      "photo": null,
      "photos": []
    },
    {
      "id": 63,
      "name": "Игорь",
      "surname": "Быстров",
      "middlename": "Анатольевич",
      "gender": "M",
      "birthDate": "1958-05-18",
      "deathDate": null,
      "birthPlace": null,
      "fatherId": null,
      "motherId": null,
      "spouseId": null,
      "biography": null,
      "photo": null,
      "photos": []
    },
    {
      "id": 64,
      "name": "Анатолий",
      "surname": "Быстров",
      "middlename": "Николаевич",
      "gender": "M",
      "birthDate": "1932-11-07",
      "deathDate": "2024-05-26",
      "birthPlace": null,
      "fatherId": null,
      "motherId": null,
      "spouseId": null,
      "biography": null,
      "photo": null,
      "photos": []
    },
    {
      "id": 65,
      "name": "Николай",
      "surname": "Быстров",
      "middlename": null,
      "gender": "M",
      "birthDate": null,
      "deathDate": null,
      "birthPlace": null,
      "fatherId": null,
      "motherId": null,
      "spouseId": null,
      "biography": null,
      "photo": null,
      "photos": []
    },
    {
      "id": 66,
      "name": "Владислав",
      "surname": "Быстров",
      "middlename": "Игоревич",
      "gender": "M",
      "birthDate": null,
      "deathDate": null,
      "birthPlace": null,
      "fatherId": null,
      "motherId": null,
      "spouseId": null,
      "biography": null,
      "photo": null,
      "photos": []
    },
    {
      "id": 67,
      "name": "Валентина",
      "surname": "Быстрова (",
      "middlename": null,
      "gender": "F",
      "birthDate": null,
      "deathDate": null,
      "birthPlace": null,
      "fatherId": null,
      "motherId": null,
      "spouseId": null,
      "biography": null,
      "photo": null,
      "photos": []
    },
    {
      "id": 68,
      "name": "Алевтина",
      "surname": "Быстрова (Матвеева)",
      "middlename": "Михайловна",
      "gender": "F",
      "birthDate": "1933-07-29",
      "deathDate": null,
      "birthPlace": null,
      "fatherId": null,
      "motherId": null,
      "spouseId": null,
      "biography": null,
      "photo": null,
      "photos": []
    },
    {
      "id": 69,
      "name": "Михаил",
      "surname": "Герасимов",
      "middlename": null,
      "gender": "M",
      "birthDate": null,
      "deathDate": null,
      "birthPlace": null,
      "fatherId": null,
      "motherId": null,
      "spouseId": null,
      "biography": null,
      "photo": null,
      "photos": []
    },
    {
      "id": 70,
      "name": "Иван",
      "surname": "Кузнецов",
      "middlename": "Федорович",
      "gender": "M",
      "birthDate": null,
      "deathDate": null,
      "birthPlace": null,
      "fatherId": null,
      "motherId": null,
      "spouseId": null,
      "biography": null,
      "photo": null,
      "photos": []
    },
    {
      "id": 71,
      "name": "Татьяна",
      "surname": "Кузнецова (Батунина)",
      "middlename": "Максимовна",
      "gender": "F",
      "birthDate": "1912-05-01",
      "deathDate": 1997,
      "birthPlace": null,
      "fatherId": null,
      "motherId": null,
      "spouseId": null,
      "biography": null,
      "photo": null,
      "photos": []
    },
    {
      "id": 72,
      "name": "Надежда",
      "surname": "Лебедева (Батунина)",
      "middlename": "Максимовна",
      "gender": "F",
      "birthDate": null,
      "deathDate": null,
      "birthPlace": null,
      "fatherId": null,
      "motherId": null,
      "spouseId": null,
      "biography": null,
      "photo": null,
      "photos": []
    },
    {
      "id": 73,
      "name": "Генадий",
      "surname": "Матвеев",
      "middlename": "Михайлович",
      "gender": "M",
      "birthDate": null,
      "deathDate": null,
      "birthPlace": null,
      "fatherId": null,
      "motherId": null,
      "spouseId": null,
      "biography": null,
      "photo": null,
      "photos": []
    },
    {
      "id": 74,
      "name": "Леонид",
      "surname": "Матвеев",
      "middlename": "Михайлович",
      "gender": "M",
      "birthDate": null,
      "deathDate": null,
      "birthPlace": null,
      "fatherId": null,
      "motherId": null,
      "spouseId": null,
      "biography": null,
      "photo": null,
      "photos": []
    },
    {
      "id": 75,
      "name": "Григорий",
      "surname": "Матвеев",
      "middlename": "Иванович",
      "gender": "M",
      "birthDate": 1900,
      "deathDate": null,
      "birthPlace": null,
      "fatherId": null,
      "motherId": null,
      "spouseId": null,
      "biography": null,
      "photo": null,
      "photos": []
    },
    {
      "id": 76,
      "name": "Станислав",
      "surname": "Матвеев",
      "middlename": "Григорьевич",
      "gender": "M",
      "birthDate": 1936,
      "deathDate": null,
      "birthPlace": null,
      "fatherId": null,
      "motherId": null,
      "spouseId": null,
      "biography": null,
      "photo": null,
      "photos": []
    },
    {
      "id": 77,
      "name": "Леонид",
      "surname": "Матвеев",
      "middlename": "Григорьевич",
      "gender": "M",
      "birthDate": 1939,
      "deathDate": null,
      "birthPlace": null,
      "fatherId": null,
      "motherId": null,
      "spouseId": null,
      "biography": null,
      "photo": null,
      "photos": []
    },
    {
      "id": 78,
      "name": "Галина",
      "surname": "Матвеева",
      "middlename": "Михайловна",
      "gender": "F",
      "birthDate": null,
      "deathDate": null,
      "birthPlace": null,
      "fatherId": null,
      "motherId": null,
      "spouseId": null,
      "biography": null,
      "photo": null,
      "photos": []
    },
    {
      "id": 79,
      "name": "Люся",
      "surname": "Матвеева",
      "middlename": "Михайловна",
      "gender": "F",
      "birthDate": null,
      "deathDate": null,
      "birthPlace": null,
      "fatherId": null,
      "motherId": null,
      "spouseId": null,
      "biography": null,
      "photo": null,
      "photos": []
    },
    {
      "id": 80,
      "name": "Людмила",
      "surname": "Матвеева",
      "middlename": "Григорьевна",
      "gender": "F",
      "birthDate": null,
      "deathDate": null,
      "birthPlace": null,
      "fatherId": null,
      "motherId": null,
      "spouseId": null,
      "biography": null,
      "photo": null,
      "photos": []
    },
    {
      "id": 81,
      "name": "Галина",
      "surname": "Матвеева",
      "middlename": "Григорьевна",
      "gender": "F",
      "birthDate": 1941,
      "deathDate": null,
      "birthPlace": null,
      "fatherId": null,
      "motherId": null,
      "spouseId": null,
      "biography": null,
      "photo": null,
      "photos": []
    },
    {
      "id": 82,
      "name": "Татьяна",
      "surname": "Матвеева",
      "middlename": "Станиславовна",
      "gender": "F",
      "birthDate": null,
      "deathDate": null,
      "birthPlace": null,
      "fatherId": null,
      "motherId": null,
      "spouseId": null,
      "biography": null,
      "photo": null,
      "photos": []
    },
    {
      "id": 83,
      "name": "Наталья",
      "surname": "Матвеева",
      "middlename": "Станиславовна",
      "gender": "F",
      "birthDate": null,
      "deathDate": null,
      "birthPlace": null,
      "fatherId": null,
      "motherId": null,
      "spouseId": null,
      "biography": null,
      "photo": null,
      "photos": []
    },
    {
      "id": 84,
      "name": "Елизавета",
      "surname": "Матвеева (Ефремова)",
      "middlename": "Петровна",
      "gender": "F",
      "birthDate": null,
      "deathDate": null,
      "birthPlace": null,
      "fatherId": null,
      "motherId": null,
      "spouseId": null,
      "biography": null,
      "photo": null,
      "photos": []
    },
    {
      "id": 85,
      "name": "Валерий",
      "surname": "Моносов",
      "middlename": "Иванович",
      "gender": "M",
      "birthDate": null,
      "deathDate": null,
      "birthPlace": null,
      "fatherId": null,
      "motherId": null,
      "spouseId": null,
      "biography": null,
      "photo": null,
      "photos": []
    },
    {
      "id": 86,
      "name": "Мария",
      "surname": "Моносова (Батунина)",
      "middlename": "Максимовна",
      "gender": "F",
      "birthDate": null,
      "deathDate": null,
      "birthPlace": null,
      "fatherId": null,
      "motherId": null,
      "spouseId": null,
      "biography": null,
      "photo": null,
      "photos": []
    },
    {
      "id": 87,
      "name": "Люба",
      "surname": "Скочимарро",
      "middlename": null,
      "gender": "F",
      "birthDate": "2012-01-06",
      "deathDate": null,
      "birthPlace": null,
      "fatherId": null,
      "motherId": null,
      "spouseId": null,
      "biography": null,
      "photo": null,
      "photos": []
    },
    {
      "id": 88,
      "name": "Лучано",
      "surname": "Скочимарро",
      "middlename": null,
      "gender": "M",
      "birthDate": "2021-04-30",
      "deathDate": null,
      "birthPlace": null,
      "fatherId": null,
      "motherId": null,
      "spouseId": null,
      "biography": null,
      "photo": null,
      "photos": []
    },
    {
      "id": 89,
      "name": "Валерия",
      "surname": "Скочимарро (Быстрова)",
      "middlename": "Игоревна",
      "gender": "F",
      "birthDate": "1983-06-08",
      "deathDate": null,
      "birthPlace": null,
      "fatherId": null,
      "motherId": null,
      "spouseId": null,
      "biography": null,
      "photo": null,
      "photos": []
    },
    {
      "id": 90,
      "name": "Владислав",
      "surname": "Быстров",
      "middlename": "Станиславович",
      "gender": "M",
      "birthDate": null,
      "deathDate": null,
      "birthPlace": null,
      "fatherId": null,
      "motherId": null,
      "spouseId": null,
      "biography": null,
      "photo": null,
      "photos": []
    }
  ]
}